sopel_remind/__init__.py
sopel_remind/backend.py
sopel_remind/config.py
sopel_remind/plugin.py
sopel_remind-0.3.0.dist-info/LICENSE.txt
sopel_remind-0.3.0.dist-info/METADATA
sopel_remind-0.3.0.dist-info/WHEEL
sopel_remind-0.3.0.dist-info/entry_points.txt
sopel_remind-0.3.0.dist-info/top_level.txt
sopel_remind-0.3.0.dist-info/RECORD
